setup.cfg
setup.py
authorize_middleware/__init__.py
authorize_middleware/auth.py
authorize_middleware/errors.py
authorize_middleware/pylons_func.py
authorize_middleware.egg-info/PKG-INFO
authorize_middleware.egg-info/SOURCES.txt
authorize_middleware.egg-info/dependency_links.txt
authorize_middleware.egg-info/requires.txt
authorize_middleware.egg-info/top_level.txt