Metadata-Version: 1.0
Name: authorize-middleware
Version: 0.1
Summary: An authorization middleware for WSGI applications
Home-page: http://hg.sandbox.lt/authorize-middleware
Author: Dalius Dobravolskas
Author-email: dalius@sandbox.lt
License: MIT
Platform: UNKNOWN
